[
  [
    {
      "cmd": "rdc open hello_triangle.rdc",
      "output": "opened: hello_triangle.rdc (no-replay mode: renderdoc unavailable)"
    },
    {
      "cmd": "rdc info",
      "output": "error: no replay loaded"
    },
    {
      "cmd": "rdc draws",
      "output": "error: no replay loaded"
    },
    {
      "cmd": "rdc pipeline 11",
      "output": "error: no replay loaded"
    },
    {
      "cmd": "rdc search \"main\"",
      "output": "error: no replay loaded"
    },
    {
      "cmd": "rdc close",
      "output": "session closed"
    }
  ],
  [
    {
      "cmd": "rdc open hello_triangle.rdc",
      "output": "opened: hello_triangle.rdc (no-replay mode: renderdoc unavailable)"
    },
    {
      "cmd": "rdc tree / --depth 1",
      "output": "error: no replay loaded"
    },
    {
      "cmd": "rdc ls /draws/11",
      "output": "error: no replay loaded"
    },
    {
      "cmd": "rdc cat /draws/11/pipeline/topology",
      "output": "error: no replay loaded"
    },
    {
      "cmd": "rdc resources -q | wc -l",
      "output": "0"
    },
    {
      "cmd": "rdc draws --json | jq \".[0].triangles\"",
      "output": "{\"error\": {\"message\": \"no replay loaded\"}}"
    },
    {
      "cmd": "rdc close",
      "output": "session closed"
    }
  ],
  [
    {
      "cmd": "rdc open hello_triangle.rdc",
      "output": "opened: hello_triangle.rdc (no-replay mode: renderdoc unavailable)"
    },
    {
      "cmd": "rdc pick-pixel 300 300 11",
      "output": "error: no replay loaded"
    },
    {
      "cmd": "rdc pixel 300 300 11",
      "output": "error: no replay loaded"
    },
    {
      "cmd": "rdc debug pixel 11 300 300",
      "output": "error: no replay loaded"
    },
    {
      "cmd": "rdc debug pixel 11 300 300 --trace",
      "output": "error: no replay loaded"
    },
    {
      "cmd": "rdc close",
      "output": "session closed"
    }
  ],
  [
    {
      "cmd": "rdc open hello_triangle.rdc",
      "output": "opened: hello_triangle.rdc (no-replay mode: renderdoc unavailable)"
    },
    {
      "cmd": "rdc draws --json",
      "output": "{\"error\": {\"message\": \"no replay loaded\"}}"
    },
    {
      "cmd": "rdc assert-count draws --expect 1 --op eq",
      "output": "error: no replay loaded"
    },
    {
      "cmd": "rdc assert-count events --expect 5 --op ge",
      "output": "error: no replay loaded"
    },
    {
      "cmd": "rdc close",
      "output": "session closed"
    }
  ],
  [
    {
      "cmd": "rdc diff before.rdc after.rdc --draws",
      "output": "error: draws query failed: both daemons failed"
    },
    {
      "cmd": "rdc diff before.rdc after.rdc --stats",
      "output": "error: stats query failed: both daemons failed"
    }
  ]
]
